jaxqualin/__init__.py
jaxqualin/data.py
jaxqualin/fit.py
jaxqualin/plot.py
jaxqualin/postprocess.py
jaxqualin/qnmode.py
jaxqualin/selection.py
jaxqualin/utils.py
jaxqualin/waveforms.py
jaxqualin-0.0.6.dist-info/METADATA
jaxqualin-0.0.6.dist-info/WHEEL
jaxqualin-0.0.6.dist-info/licenses/LICENSE
jaxqualin-0.0.6.dist-info/RECORD
